{"branch": {"product": {"binary": {"avg_time": 312447638584402.8, "meanscore": 1.0, "n_docs": 14317069415304050024424221488822878208}, "percentile": {"falsepos": 0.0}, "test": {"distinct": 3683, "exp_cost": 41873512218061494612248290656256}, "uncategorized": {"errors": 3718}}, "props": {"binary": {"auc": 1.0, "distinct": 3606}, "entities": {"non_null": 0.0}, "uncategorized": {"benchmark": 39.92741195631686}}, "related": {"binary": {"fullscore": 1.0}, "percentile": {"time": 7149370409233387.0}, "test": {"n_docs": 2322482729838517826879488}}, "set": {"binary": {"falsepos": 0.0}, "entities": {"avg_time": 238692318883183.84}, "test": {"entropy": 30.71837363591062, "exp_cost": 66646306805918548740347527168}}, "support": {"binary": {"distinct": 4532}}}, "brand": {"product": {"percentile": {"errors": 2772, "index": 9.786656583118086e+17}, "uncategorized": {"exp_cost": 577809666530745941230188891209728, "f1-score": 1.0, "recall": 1.0}}, "props": {"binary": {"exp_cost": 61702094574394441903575435898257408}, "entities": {"index": 3.8033317093332786e+20}, "percentile": {"distinct": 3559, "index": 38875982059.50901, "weighted_avg": 37.6368135541781}}, "related": {"percentile": {"falsepos": 0.0}, "uncategorized": {"n_docs": 196768294887030380351188893696}}, "set": {"binary": {"distinct": 3426, "loss": 0.0}, "percentile": {"index": 1.8809668029992184e+16, "non_null": 0.0}, "test": {"time": 469872082433796.56}}, "support": {"binary": {"meanscore": 1.0}, "percentile": {"exp_cost": 28309630439461802163341303874181922816}, "test": {"prediction_time": 7.673064632608469e+21}, "uncategorized": {"loss": 0.0}}}, "reports": {"product": {"percentile": {"time": 1642038118870.5957}, "test": {"n_docs": 243108517393019817087725469696}, "uncategorized": {"entropy": 48.3070305108041}}, "props": {"entities": {"falsepos": 0.0, "non_null": 0.0}, "uncategorized": {"index": 12605250804600.613, "size": 1308374729234930531123434000220160}}, "related": {"binary": {"auc": 1.0, "time": 2310193324195.5938}, "entities": {"avg_time": 17184110439151.678}, "percentile": {"precision": 1.0}, "test": {"f1-score": 1.0, "prediction_time": 70148318057.73189}}, "set": {"binary": {"f1-score": 1.0, "non_null": 0.0, "size": 19063718191815572907010371445623619584}, "percentile": {"non_null": 0.0}, "test": {"auc": 1.0, "distinct": 3172}, "uncategorized": {"weighted_avg": 47.88344107885344}}, "support": {"binary": {"exp_cost": 227965082036729140273125438065134184431616, "size": 1271667213166904447286661980857422301846568960}, "entities": {"precision": 1.0}, "percentile": {"avg_time": 28122437735450.426}, "test": {"exp_cost": 9507028074024196767452997003415388160}, "uncategorized": {"avg_time": 3783704676357111.0}}}, "results": {"product": {"binary": {"n_docs": 910948533881371188852900757504}, "uncategorized": {"loss": 0.0}}, "props": {"percentile": {"index": 360852360.88265616}, "test": {"non_null": 0.0, "weighted_avg": 36.23087843492175}}, "related": {"binary": {"falsepos": 0.0, "loss": 0.0}, "entities": {"prediction_time": 352053924.02603036}, "percentile": {"errors": 2595}, "test": {"distinct": 3085}, "uncategorized": {"loss": 0.0}}, "set": {"percentile": {"time": 2050424969899.2705}, "test": {"precision": 1.0}}, "support": {"binary": {"distinct": 3547}, "test": {"f1-score": 1.0}, "uncategorized": {"loss": 0.0}}}, "train": {"product": {"binary": {"f1-score": 1.0, "weighted_avg": 46.92259614192032}, "entities": {"distinct": 3386, "falsepos": 0.0}, "percentile": {"auc": 1.0}}, "props": {"test": {"distinct": 2829}}, "related": {"entities": {"prediction_time": 5676396766.6121645}, "percentile": {"time": 5049928300124.913}, "test": {"errors": 3322}, "uncategorized": {"time": 225884238.90245554}}, "set": {"entities": {"loss": 0.0}, "percentile": {"prediction_time": 1935663323995.398}, "test": {"benchmark": 34.794068667901435, "recall": 1.0}}, "support": {"binary": {"falsepos": 0.0}, "entities": {"auc": 1.0}, "percentile": {"benchmark": 31.581561250886537}, "uncategorized": {"time": 120615502928130.52}}}}