{"branch": {"product": {"binary": {"avg_time": 1577593940.2007477, "meanscore": 1.0, "n_docs": 3047502987257432659460096}, "percentile": {"falsepos": 0.0}, "test": {"distinct": 2319, "exp_cost": 994290876926310350848}, "uncategorized": {"errors": 2349}}, "props": {"binary": {"auc": 1.0, "distinct": 2291}, "entities": {"non_null": 0.0}, "uncategorized": {"benchmark": 25.319354741488006}}, "related": {"binary": {"fullscore": 1.0}, "percentile": {"time": 8734681178.517996}, "test": {"n_docs": 20029266005459788}}, "set": {"binary": {"falsepos": 0.0}, "entities": {"avg_time": 1178536159.951782}, "test": {"entropy": 19.40851346129228, "exp_cost": 20592453346800558080}}, "support": {"binary": {"distinct": 2855}}}, "brand": {"product": {"percentile": {"errors": 1757, "index": 251102451247.51944}, "uncategorized": {"exp_cost": 7794610164556707659776, "f1-score": 1.0, "recall": 1.0}}, "props": {"binary": {"exp_cost": 100795324662441926721536}, "entities": {"index": 9002568179137.184}, "percentile": {"distinct": 2254, "index": 4882798.290216993, "weighted_avg": 23.847527980483996}}, "related": {"percentile": {"falsepos": 0.0}, "uncategorized": {"n_docs": 39985147965061365760}}, "set": {"binary": {"distinct": 2153, "loss": 0.0}, "percentile": {"index": 19231272515.746952, "non_null": 0.0}, "test": {"time": 2062724507.0547097}}, "support": {"binary": {"meanscore": 1.0}, "percentile": {"exp_cost": 5855822984282120237613056}, "test": {"prediction_time": 68865662630629.2}, "uncategorized": {"loss": 0.0}}}, "reports": {"product": {"percentile": {"time": 49040272.05287711}, "test": {"n_docs": 59855769551836438528}, "uncategorized": {"entropy": 30.44626809549934}}, "props": {"entities": {"falsepos": 0.0, "non_null": 0.0}, "uncategorized": {"index": 211903711.65935168, "size": 18878202612934963625984}}, "related": {"binary": {"auc": 1.0, "time": 63733242.14118505}, "entities": {"avg_time": 222515145.52458453}, "percentile": {"precision": 1.0}, "test": {"f1-score": 1.0, "prediction_time": 8435852.241835676}}, "set": {"binary": {"f1-score": 1.0, "non_null": 0.0, "size": 4052714556315483190067200}, "percentile": {"non_null": 0.0}, "test": {"auc": 1.0, "distinct": 2003}, "uncategorized": {"weighted_avg": 30.18884190321513}}, "support": {"binary": {"exp_cost": 1121476329011335303155154944, "size": 536700601100952321109893578752}, "entities": {"precision": 1.0}, "percentile": {"avg_time": 265772887.60649243}, "test": {"exp_cost": 3150136141634340846043136}, "uncategorized": {"avg_time": 7781311225.483359}}}, "results": {"product": {"binary": {"n_docs": 142769089874147901440}, "uncategorized": {"loss": 0.0}}, "props": {"percentile": {"index": 239812.5180631259}, "test": {"non_null": 0.0, "weighted_avg": 22.89799744638935}}, "related": {"binary": {"falsepos": 0.0, "loss": 0.0}, "entities": {"prediction_time": 315955.01942420175}, "percentile": {"errors": 1643}, "test": {"distinct": 1961}, "uncategorized": {"loss": 0.0}}, "set": {"percentile": {"time": 63700724.896407954}, "test": {"precision": 1.0}}, "support": {"binary": {"distinct": 2249}, "test": {"f1-score": 1.0}, "uncategorized": {"loss": 0.0}}}, "train": {"product": {"binary": {"f1-score": 1.0, "weighted_avg": 29.408583869927273}, "entities": {"distinct": 2138, "falsepos": 0.0}, "percentile": {"auc": 1.0}}, "props": {"test": {"distinct": 1784}}, "related": {"entities": {"prediction_time": 1321272.9380984178}, "percentile": {"time": 120926134.542085}, "test": {"errors": 2104}, "uncategorized": {"time": 247067.5186341681}}, "set": {"entities": {"loss": 0.0}, "percentile": {"prediction_time": 60608693.87242956}, "test": {"benchmark": 21.75942652153279, "recall": 1.0}}, "support": {"binary": {"falsepos": 0.0}, "entities": {"auc": 1.0}, "percentile": {"benchmark": 20.239210534544487}, "uncategorized": {"time": 977878565.8486015}}}}