{"branch": {"product": {"binary": {"avg_time": 24985.61278868632, "meanscore": 1.0, "n_docs": 7855088016754}, "percentile": {"falsepos": 0.0}, "test": {"distinct": 1075, "exp_cost": 194353888956}, "uncategorized": {"errors": 1102}}, "props": {"binary": {"auc": 1.0, "distinct": 1064}, "entities": {"non_null": 0.0}, "uncategorized": {"benchmark": 11.84773121092951}}, "related": {"binary": {"fullscore": 0.9999999999233778}, "percentile": {"time": 40987.00966037605}, "test": {"n_docs": 2214613024}}, "set": {"binary": {"falsepos": 0.0}, "entities": {"avg_time": 15484.084529310629}, "test": {"entropy": 9.157241157199651, "exp_cost": 34312062374}}, "support": {"binary": {"distinct": 1327}}}, "brand": {"product": {"percentile": {"errors": 824, "index": 237397.30802459782}, "uncategorized": {"exp_cost": 785659724367, "f1-score": 1.0, "recall": 1.0}}, "props": {"binary": {"exp_cost": 1934273221082}, "entities": {"index": 960175.7190866128}, "percentile": {"distinct": 1070, "index": 1494.4868600922423, "weighted_avg": 11.336423069717439}}, "related": {"percentile": {"falsepos": 0.0}, "uncategorized": {"n_docs": 88722970293}}, "set": {"binary": {"distinct": 1001, "loss": 0.0}, "percentile": {"index": 50262.80852856801, "non_null": 0.0}, "test": {"time": 23853.978529810913}}, "support": {"binary": {"meanscore": 1.0}, "percentile": {"exp_cost": 13447606007127}, "test": {"prediction_time": 2760483.4000573843}, "uncategorized": {"loss": 0.0}}}, "reports": {"product": {"percentile": {"time": 4098.910167868073}, "test": {"n_docs": 64662273687}, "uncategorized": {"entropy": 13.873024061228877}}, "props": {"entities": {"falsepos": 0.0, "non_null": 0.0}, "uncategorized": {"index": 8549.515150998786, "size": 1291082423252}}, "related": {"binary": {"auc": 1.0, "time": 5096.4516215761605}, "entities": {"avg_time": 7437.204287377408}, "percentile": {"precision": 1.0}, "test": {"f1-score": 0.999999999999942, "prediction_time": 2099.7329204052144}}, "set": {"binary": {"f1-score": 0.9999999999753629, "non_null": 0.0, "size": 9191849343328}, "percentile": {"non_null": 0.0}, "test": {"auc": 0.9999999999731948, "distinct": 926}, "uncategorized": {"weighted_avg": 14.058146430144152}}, "support": {"binary": {"exp_cost": 144451145135299, "size": 2941725404072005}, "entities": {"precision": 0.9999999999989276}, "percentile": {"avg_time": 7688.956305539083}, "test": {"exp_cost": 18302038468615}, "uncategorized": {"avg_time": 40383.77104969679}}}, "results": {"product": {"binary": {"n_docs": 118553759409}, "uncategorized": {"loss": 0.0}}, "props": {"percentile": {"index": 303.06521441906864}, "test": {"non_null": 2.1975021802234096e-10, "weighted_avg": 10.594822736394812}}, "related": {"binary": {"falsepos": 0.0, "loss": 0.0}, "entities": {"prediction_time": 458.6325687678398}, "percentile": {"errors": 783}, "test": {"distinct": 905}, "uncategorized": {"loss": 0.0}}, "set": {"percentile": {"time": 4126.454512316038}, "test": {"precision": 1.0}}, "support": {"binary": {"distinct": 1069}, "test": {"f1-score": 1.0}, "uncategorized": {"loss": 0.0}}}, "train": {"product": {"binary": {"f1-score": 0.9999999999999551, "weighted_avg": 13.664536656706927}, "entities": {"distinct": 991, "falsepos": 5.042510853314752e-11}, "percentile": {"auc": 1.0}}, "props": {"test": {"distinct": 821}}, "related": {"entities": {"prediction_time": 625.1073472282989}, "percentile": {"time": 5525.952521018589}, "test": {"errors": 985}, "uncategorized": {"time": 431.48110054149595}}, "set": {"entities": {"loss": 0.0}, "percentile": {"prediction_time": 4521.207920064112}, "test": {"benchmark": 9.740753307214534, "recall": 0.9999999999805727}}, "support": {"binary": {"falsepos": 3.3306690738754696e-15}, "entities": {"auc": 0.9999999999999786}, "percentile": {"benchmark": 9.67138483877531}, "uncategorized": {"time": 19851.686608628635}}}}