{"branch": {"product": {"binary": {"avg_time": 777.6628285465562, "meanscore": 0.9999999999091362, "n_docs": 2099823333}, "percentile": {"falsepos": 6.737943536450075e-13}, "test": {"distinct": 698, "exp_cost": 215440351}, "uncategorized": {"errors": 698}}, "props": {"binary": {"auc": 0.9999999999999992, "distinct": 694}, "entities": {"non_null": 1.3298125933758342e-09}, "uncategorized": {"benchmark": 7.698053707300296}}, "related": {"binary": {"fullscore": 0.999979135676424}, "percentile": {"time": 823.2666637415417}, "test": {"n_docs": 12596547}}, "set": {"binary": {"falsepos": 2.4328206116308593e-11}, "entities": {"avg_time": 499.066412729106}, "test": {"entropy": 5.834628652424229, "exp_cost": 89976910}}, "support": {"binary": {"distinct": 857}}}, "brand": {"product": {"percentile": {"errors": 541, "index": 2935.942149999885}, "uncategorized": {"exp_cost": 719727235, "f1-score": 0.9999999999965239, "recall": 0.9999999999998581}}, "props": {"binary": {"exp_cost": 860090848}, "entities": {"index": 8190.359466866847}, "percentile": {"distinct": 694, "index": 105.52663522089614, "weighted_avg": 7.358545776339568}}, "related": {"percentile": {"falsepos": 4.440892098500626e-16}, "uncategorized": {"n_docs": 156628267}}, "set": {"binary": {"distinct": 657, "loss": 1.9983021015690383e-08}, "percentile": {"index": 984.7235744331963, "non_null": 1.7670309659933991e-12}, "test": {"time": 759.4952066968128}}, "support": {"binary": {"meanscore": 0.9999999999999969}, "percentile": {"exp_cost": 3610721904}, "test": {"prediction_time": 13803.140649281211}, "uncategorized": {"loss": 2.993383318994347e-12}}}, "reports": {"product": {"percentile": {"time": 216.8852615492794}, "test": {"n_docs": 146799382}, "uncategorized": {"entropy": 8.927281365178986}}, "props": {"entities": {"falsepos": 7.67145214020104e-09, "non_null": 1.7127987916865095e-10}, "uncategorized": {"index": 360.97837594646927, "size": 1248606157}}, "related": {"binary": {"auc": 0.9999999991009187, "time": 241.32347428895582}, "entities": {"avg_time": 297.7126840997606}, "percentile": {"precision": 0.999999999999917}, "test": {"f1-score": 0.9999996902489069, "prediction_time": 181.9939444973184}}, "set": {"binary": {"f1-score": 0.9999790591242989, "non_null": 0.0, "size": 1999046513}, "percentile": {"non_null": 1.3349410465934852e-10}, "test": {"auc": 0.9999890591297668, "distinct": 582}, "uncategorized": {"weighted_avg": 9.114063313852514}}, "support": {"binary": {"exp_cost": 20090172510, "size": 115793993704}, "entities": {"precision": 0.9999966934323663}, "percentile": {"avg_time": 312.8390204333365}, "test": {"exp_cost": 5344944068}, "uncategorized": {"avg_time": 756.9964334391427}}}, "results": {"product": {"binary": {"n_docs": 219267620}, "uncategorized": {"loss": 3.3306690738754696e-16}}, "props": {"percentile": {"index": 37.23911713513342}, "test": {"non_null": 2.2716388128118936e-05, "weighted_avg": 6.855346496545339}}, "related": {"binary": {"falsepos": 2.741740168232809e-11, "loss": 6.661338147750939e-16}, "entities": {"prediction_time": 60.953947644374786}, "percentile": {"errors": 524}, "test": {"distinct": 579}, "uncategorized": {"loss": 6.439293542825908e-15}}, "set": {"percentile": {"time": 215.2525598166464}, "test": {"precision": 0.999999999988683}}, "support": {"binary": {"distinct": 672}, "test": {"f1-score": 1.0}, "uncategorized": {"loss": 1.6691648063726916e-10}}}, "train": {"product": {"binary": {"f1-score": 0.9999996899301326, "weighted_avg": 8.796127722939913}, "entities": {"distinct": 637, "falsepos": 1.3411014971431712e-05}, "percentile": {"auc": 0.9999999998724387}}, "props": {"test": {"distinct": 534}}, "related": {"entities": {"prediction_time": 55.0569351452412}, "percentile": {"time": 258.8565101937779}, "test": {"errors": 627}, "uncategorized": {"time": 58.51924498869865}}, "set": {"entities": {"loss": 3.3306690738754696e-16}, "percentile": {"prediction_time": 226.88800155737744}, "test": {"benchmark": 6.209347021028401, "recall": 0.9999818290320605}}, "support": {"binary": {"falsepos": 6.153005593922956e-08}, "entities": {"auc": 0.9999997558448215}, "percentile": {"benchmark": 6.43632575987754}, "uncategorized": {"time": 711.8824643365191}}}}