{"branch": {"product": {"binary": {"avg_time": 2.9303271077967833e+20, "meanscore": 1.0, "n_docs": 7107458681621703626392187845289696003289466873577472}, "percentile": {"falsepos": 0.0}, "test": {"distinct": 5308, "exp_cost": 221735743836005222847863048844405220541726720}, "uncategorized": {"errors": 5327}}, "props": {"binary": {"auc": 1.0, "distinct": 5072}, "entities": {"non_null": 0.0}, "uncategorized": {"benchmark": 56.45860904253024}}, "related": {"binary": {"fullscore": 1.0}, "percentile": {"time": 1.7858569791047077e+22}, "test": {"n_docs": 2222417140295515497429167595585536}}, "set": {"binary": {"falsepos": 0.0}, "entities": {"avg_time": 1.3417265624666794e+20}, "test": {"entropy": 43.724723713167876, "exp_cost": 6108107126826789936640221589286837813248}}, "support": {"binary": {"distinct": 6422}}}, "brand": {"product": {"percentile": {"errors": 3991, "index": 5.486448968202043e+25}, "uncategorized": {"exp_cost": 5450849480958958050007151912390673356885590016, "f1-score": 1.0, "recall": 1.0}}, "props": {"binary": {"exp_cost": 1639508022018661994748799832056964249166079328256}, "entities": {"index": 1.7343553535757883e+29}, "percentile": {"distinct": 5036, "index": 1221210767996313.5, "weighted_avg": 53.97929798528875}}, "related": {"percentile": {"falsepos": 0.0}, "uncategorized": {"n_docs": 44368678146054299792715289748364725321728}}, "set": {"binary": {"distinct": 4940, "loss": 0.0}, "percentile": {"index": 1.7183144755536405e+23, "non_null": 0.0}, "test": {"time": 4.460820051414329e+20}}, "support": {"binary": {"meanscore": 1.0}, "percentile": {"exp_cost": 4671467115903785110031005774209514304307298180268032}, "test": {"prediction_time": 1.261279681809762e+31}, "uncategorized": {"loss": 0.0}}}, "reports": {"product": {"percentile": {"time": 2.748998793996134e+17}, "test": {"n_docs": 15423988089041484606112945973642120921088}, "uncategorized": {"entropy": 68.50768603123657}}, "props": {"entities": {"falsepos": 0.0, "non_null": 0.0}, "uncategorized": {"index": 3.771117717457226e+18, "size": 24998565737304699937810340375041488081865670656}}, "related": {"binary": {"auc": 1.0, "time": 3.162942517674726e+17}, "entities": {"avg_time": 7.02804441637901e+18}, "percentile": {"precision": 1.0}, "test": {"f1-score": 1.0, "prediction_time": 1370813794449557.8}}, "set": {"binary": {"f1-score": 1.0, "non_null": 0.0, "size": 12981739308830299086203302545166070211710996910702592}, "percentile": {"non_null": 0.0}, "test": {"auc": 1.0, "distinct": 4535}, "uncategorized": {"weighted_avg": 68.17862326379014}}, "support": {"binary": {"exp_cost": 2630298497053366834169874046674589369305373873389569048576, "size": 1170897801089466591964439429985540295900488507608188812810780672}, "entities": {"precision": 1.0}, "percentile": {"avg_time": 2.8840722127642264e+19}, "test": {"exp_cost": 2290372593311082064474693424717676156316590039629824}, "uncategorized": {"avg_time": 1.9583092296580214e+22}}}, "results": {"product": {"binary": {"n_docs": 124511621574301225796012087405054697406464}, "uncategorized": {"loss": 0.0}}, "props": {"percentile": {"index": 1497910329777.8323}, "test": {"non_null": 0.0, "weighted_avg": 51.28702027351185}}, "related": {"binary": {"falsepos": 0.0, "loss": 0.0}, "entities": {"prediction_time": 1428249187853.3662}, "percentile": {"errors": 3691}, "test": {"distinct": 4329}, "uncategorized": {"loss": 0.0}}, "set": {"percentile": {"time": 3.467075616877271e+17}, "test": {"precision": 1.0}}, "support": {"binary": {"distinct": 5093}, "test": {"f1-score": 1.0}, "uncategorized": {"loss": 0.0}}}, "train": {"product": {"binary": {"f1-score": 1.0, "weighted_avg": 66.68502118632955}, "entities": {"distinct": 4882, "falsepos": 0.0}, "percentile": {"auc": 1.0}}, "props": {"test": {"distinct": 4001}}, "related": {"entities": {"prediction_time": 95358013225324.48}, "percentile": {"time": 7.56785458164738e+17}, "test": {"errors": 4765}, "uncategorized": {"time": 550779875840.0145}}, "set": {"entities": {"loss": 0.0}, "percentile": {"prediction_time": 3.6591216515451034e+17}, "test": {"benchmark": 48.82722041415664, "recall": 1.0}}, "support": {"binary": {"falsepos": 0.0}, "entities": {"auc": 1.0}, "percentile": {"benchmark": 45.314970003831164}, "uncategorized": {"time": 1.3132407605973921e+20}}}}