{"branch": {"product": {"binary": {"avg_time": 218818385101938.72, "meanscore": 1.0, "n_docs": 8347404662044711661141008521736749056}, "percentile": {"falsepos": 0.0}, "test": {"distinct": 3663, "exp_cost": 23962381316315950943546682376192}, "uncategorized": {"errors": 3701}}, "props": {"binary": {"auc": 1.0, "distinct": 3585}, "entities": {"non_null": 0.0}, "uncategorized": {"benchmark": 39.565858260311494}}, "related": {"binary": {"fullscore": 1.0}, "percentile": {"time": 5733576534691890.0}, "test": {"n_docs": 1315791011616039064567808}}, "set": {"binary": {"falsepos": 0.0}, "entities": {"avg_time": 170815485470347.47}, "test": {"entropy": 30.41544030763725, "exp_cost": 31628557709108841330241437696}}, "support": {"binary": {"distinct": 4484}}}, "brand": {"product": {"percentile": {"errors": 2741, "index": 5.584195676062628e+17}, "uncategorized": {"exp_cost": 279678898171144852414656749240320, "f1-score": 1.0, "recall": 1.0}}, "props": {"binary": {"exp_cost": 30061475460932691592976205793460224}, "entities": {"index": 2.2029082564198505e+20}, "percentile": {"distinct": 3516, "index": 28660427521.199566, "weighted_avg": 37.292869176879016}}, "related": {"percentile": {"falsepos": 0.0}, "uncategorized": {"n_docs": 109475419086060989849352011776}}, "set": {"binary": {"distinct": 3369, "loss": 0.0}, "percentile": {"index": 1.404882256720959e+16, "non_null": 0.0}, "test": {"time": 352282471221894.3}}, "support": {"binary": {"meanscore": 1.0}, "percentile": {"exp_cost": 15844356510350118372784597044327088128}, "test": {"prediction_time": 4.1050152908010884e+21}, "uncategorized": {"loss": 0.0}}}, "reports": {"product": {"percentile": {"time": 1240276382642.6497}, "test": {"n_docs": 191710589283937398152155365376}, "uncategorized": {"entropy": 47.70519902599463}}, "props": {"entities": {"falsepos": 0.0, "non_null": 0.0}, "uncategorized": {"index": 8458157819417.004, "size": 795626503126280479512216213651456}}, "related": {"binary": {"auc": 1.0, "time": 1501678605006.726}, "entities": {"avg_time": 13026101911280.744}, "percentile": {"precision": 1.0}, "test": {"f1-score": 1.0, "prediction_time": 56733578705.10266}}, "set": {"binary": {"f1-score": 1.0, "non_null": 0.0, "size": 8195769207793862960011051093010153472}, "percentile": {"non_null": 0.0}, "test": {"auc": 1.0, "distinct": 3137}, "uncategorized": {"weighted_avg": 47.39219312430517}}, "support": {"binary": {"exp_cost": 100687258833023218100278035503827744980992, "size": 449852900847288801457384154662174809254789120}, "entities": {"precision": 1.0}, "percentile": {"avg_time": 18581158632505.484}, "test": {"exp_cost": 4961952484567520371475673305946521600}, "uncategorized": {"avg_time": 3062596161607737.5}}}, "results": {"product": {"binary": {"n_docs": 411768628021684915693099679744}, "uncategorized": {"loss": 0.0}}, "props": {"percentile": {"index": 297341375.09009254}, "test": {"non_null": 0.0, "weighted_avg": 35.971719500098175}}, "related": {"binary": {"falsepos": 0.0, "loss": 0.0}, "entities": {"prediction_time": 348875130.70834684}, "percentile": {"errors": 2580}, "test": {"distinct": 3062}, "uncategorized": {"loss": 0.0}}, "set": {"percentile": {"time": 1725196095606.7166}, "test": {"precision": 1.0}}, "support": {"binary": {"distinct": 3490}, "test": {"f1-score": 1.0}, "uncategorized": {"loss": 0.0}}}, "train": {"product": {"binary": {"f1-score": 1.0, "weighted_avg": 46.43936074691492}, "entities": {"distinct": 3342, "falsepos": 0.0}, "percentile": {"auc": 1.0}}, "props": {"test": {"distinct": 2797}}, "related": {"entities": {"prediction_time": 4059343022.456351}, "percentile": {"time": 3781518629164.023}, "test": {"errors": 3299}, "uncategorized": {"time": 182413548.40787548}}, "set": {"entities": {"loss": 0.0}, "percentile": {"prediction_time": 1510183968826.3757}, "test": {"benchmark": 34.399466390847195, "recall": 1.0}}, "support": {"binary": {"falsepos": 0.0}, "entities": {"auc": 1.0}, "percentile": {"benchmark": 31.338103591832827}, "uncategorized": {"time": 84561880461187.48}}}}