{"branch": {"product": {"binary": {"avg_time": 2.9678833431316566e+19, "meanscore": 1.0, "n_docs": 19549794557211081831317771000255123663951159623680}, "percentile": {"falsepos": 0.0}, "test": {"distinct": 5039, "exp_cost": 939739151259076099082411893921241624477696}, "uncategorized": {"errors": 5044}}, "props": {"binary": {"auc": 1.0, "distinct": 4831}, "entities": {"non_null": 0.0}, "uncategorized": {"benchmark": 53.68097982007481}}, "related": {"binary": {"fullscore": 1.0}, "percentile": {"time": 1.5541685130786924e+21}, "test": {"n_docs": 64695928201169603330313516220416}}, "set": {"binary": {"falsepos": 0.0}, "entities": {"avg_time": 1.6417958621475471e+19}, "test": {"entropy": 41.45067494686841, "exp_cost": 75334117795836345786329689444428283904}}, "support": {"binary": {"distinct": 6091}}}, "brand": {"product": {"percentile": {"errors": 3771, "index": 2.2928391515993206e+24}, "uncategorized": {"exp_cost": 26483118549667832878478207384888095614697472, "f1-score": 1.0, "recall": 1.0}}, "props": {"binary": {"exp_cost": 8695350226587619965441926732773468129607024640}, "entities": {"index": 5.117901104094039e+27}, "percentile": {"distinct": 4794, "index": 220077524724176.72, "weighted_avg": 51.12682424498901}}, "related": {"percentile": {"falsepos": 0.0}, "uncategorized": {"n_docs": 430407454843476663837221645667035774976}}, "set": {"binary": {"distinct": 4655, "loss": 0.0}, "percentile": {"index": 1.2610117802014162e+22, "non_null": 0.0}, "test": {"time": 4.786691542112602e+19}}, "support": {"binary": {"meanscore": 1.0}, "percentile": {"exp_cost": 24782953907395393662575902582201373517000237645824}, "test": {"prediction_time": 3.48948165465483e+29}, "uncategorized": {"loss": 0.0}}}, "reports": {"product": {"percentile": {"time": 3.918885701953895e+16}, "test": {"n_docs": 325735722338737861825573131802569080832}, "uncategorized": {"entropy": 65.27979050737828}}, "props": {"entities": {"falsepos": 0.0, "non_null": 0.0}, "uncategorized": {"index": 4.310964612520368e+17, "size": 96601467608715027826578976311007285579087872}}, "related": {"binary": {"auc": 1.0, "time": 4.402699694005513e+16}, "entities": {"avg_time": 7.924520937921147e+17}, "percentile": {"precision": 1.0}, "test": {"f1-score": 1.0, "prediction_time": 320457670461921.7}}, "set": {"binary": {"f1-score": 1.0, "non_null": 0.0, "size": 26484869679902032249843211883197978046230572302336}, "percentile": {"non_null": 0.0}, "test": {"auc": 1.0, "distinct": 4299}, "uncategorized": {"weighted_avg": 64.73427720926118}}, "support": {"binary": {"exp_cost": 4793903783180406443201267027679446402135825540605542400, "size": 1423163761578738778606979924015005681165790027247811062398976}, "entities": {"precision": 1.0}, "percentile": {"avg_time": 2.4835395628775537e+18}, "test": {"exp_cost": 5882114262166653589304783982705709074232119394304}, "uncategorized": {"avg_time": 1.2820022575279117e+21}}}, "results": {"product": {"binary": {"n_docs": 1805436168924346214452890199597961445376}, "uncategorized": {"loss": 0.0}}, "props": {"percentile": {"index": 347145045442.1914}, "test": {"non_null": 0.0, "weighted_avg": 48.81723900893926}}, "related": {"binary": {"falsepos": 0.0, "loss": 0.0}, "entities": {"prediction_time": 340331097413.8055}, "percentile": {"errors": 3506}, "test": {"distinct": 4135}, "uncategorized": {"loss": 0.0}}, "set": {"percentile": {"time": 4.3127393493400424e+16}, "test": {"precision": 1.0}}, "support": {"binary": {"distinct": 4809}, "test": {"f1-score": 1.0}, "uncategorized": {"loss": 0.0}}}, "train": {"product": {"binary": {"f1-score": 1.0, "weighted_avg": 63.3884537377693}, "entities": {"distinct": 4608, "falsepos": 0.0}, "percentile": {"auc": 1.0}}, "props": {"test": {"distinct": 3826}}, "related": {"entities": {"prediction_time": 15579909829798.967}, "percentile": {"time": 1.090528994923023e+17}, "test": {"errors": 4515}, "uncategorized": {"time": 144786599071.82074}}, "set": {"entities": {"loss": 0.0}, "percentile": {"prediction_time": 4.781619066001296e+16}, "test": {"benchmark": 46.651953056711285, "recall": 1.0}}, "support": {"binary": {"falsepos": 0.0}, "entities": {"auc": 1.0}, "percentile": {"benchmark": 42.90884231419595}, "uncategorized": {"time": 1.0902020989432588e+19}}}}