{"branch": {"product": {"binary": {"avg_time": 4.463443961091452e+16, "meanscore": 1.0, "n_docs": 2430031083825771012929138415320117865873408}, "percentile": {"falsepos": 0.0}, "test": {"distinct": 4255, "exp_cost": 847745262682229487416083846604521472}, "uncategorized": {"errors": 4288}}, "props": {"binary": {"auc": 1.0, "distinct": 4154}, "entities": {"non_null": 0.0}, "uncategorized": {"benchmark": 45.98007607164687}}, "related": {"binary": {"fullscore": 1.0}, "percentile": {"time": 1.6738912616914266e+18}, "test": {"n_docs": 2257500550267397135268839424}}, "set": {"binary": {"falsepos": 0.0}, "entities": {"avg_time": 3.4971560793903164e+16}, "test": {"entropy": 35.266406211849265, "exp_cost": 357648107776459611824272841900032}}, "support": {"binary": {"distinct": 5199}}}, "brand": {"product": {"percentile": {"errors": 3190, "index": 3.897505232668476e+20}, "uncategorized": {"exp_cost": 11860655478757120046452582005071675392, "f1-score": 1.0, "recall": 1.0}}, "props": {"binary": {"exp_cost": 3639704526543367736074041251581036331008}, "entities": {"index": 4.3310433425788856e+23}, "percentile": {"distinct": 4075, "index": 1120569836215.0542, "weighted_avg": 43.203629925887725}}, "related": {"percentile": {"falsepos": 0.0}, "uncategorized": {"n_docs": 1368696752850735649217427575668736}}, "set": {"binary": {"distinct": 3935, "loss": 0.0}, "percentile": {"index": 6.044499092701358e+18, "non_null": 0.0}, "test": {"time": 6.717334021332863e+16}}, "support": {"binary": {"meanscore": 1.0}, "percentile": {"exp_cost": 4890045009318891050700590685795488758759424}, "test": {"prediction_time": 1.4665247013863297e+25}, "uncategorized": {"loss": 0.0}}}, "reports": {"product": {"percentile": {"time": 131230622670005.58}, "test": {"n_docs": 3015805016791804967206483367297024}, "uncategorized": {"entropy": 55.31428366853424}}, "props": {"entities": {"falsepos": 0.0, "non_null": 0.0}, "uncategorized": {"index": 1045890997485490.2, "size": 42183456041765545190186497545452126208}}, "related": {"binary": {"auc": 1.0, "time": 132955213106053.67}, "entities": {"avg_time": 1602709464631632.0}, "percentile": {"precision": 1.0}, "test": {"f1-score": 1.0, "prediction_time": 2806686546852.454}}, "set": {"binary": {"f1-score": 1.0, "non_null": 0.0, "size": 2130299887026452489796673770233055437389824}, "percentile": {"non_null": 0.0}, "test": {"auc": 1.0, "distinct": 3644}, "uncategorized": {"weighted_avg": 55.03423714226758}}, "support": {"binary": {"exp_cost": 126411174857606601788058764680537844573014065152, "size": 2083084632675237986371017114422194127276727192256512}, "entities": {"precision": 1.0}, "percentile": {"avg_time": 2938832765230461.0}, "test": {"exp_cost": 1012124317050296795714624286579972003332096}, "uncategorized": {"avg_time": 8.446784184855523e+17}}}, "results": {"product": {"binary": {"n_docs": 7866339359263459501416904721956864}, "uncategorized": {"loss": 0.0}}, "props": {"percentile": {"index": 6699624280.110977}, "test": {"non_null": 0.0, "weighted_avg": 41.76689234466873}}, "related": {"binary": {"falsepos": 0.0, "loss": 0.0}, "entities": {"prediction_time": 6540466646.517848}, "percentile": {"errors": 2978}, "test": {"distinct": 3549}, "uncategorized": {"loss": 0.0}}, "set": {"percentile": {"time": 141551112944523.4}, "test": {"precision": 1.0}}, "support": {"binary": {"distinct": 4068}, "test": {"f1-score": 1.0}, "uncategorized": {"loss": 0.0}}}, "train": {"product": {"binary": {"f1-score": 1.0, "weighted_avg": 53.906549007498356}, "entities": {"distinct": 3890, "falsepos": 0.0}, "percentile": {"auc": 1.0}}, "props": {"test": {"distinct": 3261}}, "related": {"entities": {"prediction_time": 169841515157.84805}, "percentile": {"time": 355482300335221.94}, "test": {"errors": 3832}, "uncategorized": {"time": 3204050578.7280626}}, "set": {"entities": {"loss": 0.0}, "percentile": {"prediction_time": 141732080447885.0}, "test": {"benchmark": 40.04950138709293, "recall": 1.0}}, "support": {"binary": {"falsepos": 0.0}, "entities": {"auc": 1.0}, "percentile": {"benchmark": 36.257535765879716}, "uncategorized": {"time": 1.4493426139141908e+16}}}}