{"branch": {"product": {"binary": {"avg_time": 10.005965091846509, "meanscore": 0.989196507434361, "n_docs": 55085}, "percentile": {"falsepos": 0.018795576381505086}, "test": {"distinct": 204, "exp_cost": 35449}, "uncategorized": {"errors": 214}}, "props": {"binary": {"auc": 0.9951717567214307, "distinct": 231}, "entities": {"non_null": 0.019299120255956814}, "uncategorized": {"benchmark": 2.451402930381558}}, "related": {"binary": {"fullscore": 0.9195010076072065}, "percentile": {"time": 8.732460501490321}, "test": {"n_docs": 38481}}, "set": {"binary": {"falsepos": 0.014689444489057957}, "entities": {"avg_time": 8.117089400319736}, "test": {"entropy": 1.7530350123464027, "exp_cost": 31481}}, "support": {"binary": {"distinct": 242}}}, "brand": {"product": {"percentile": {"errors": 173, "index": 13.13155154606324}, "uncategorized": {"exp_cost": 48994, "f1-score": 0.9806103007716896, "recall": 0.9928072131535048}}, "props": {"binary": {"exp_cost": 62027}, "entities": {"index": 14.697398689974756}, "percentile": {"distinct": 221, "index": 4.85556040576546, "weighted_avg": 2.39438756057199}}, "related": {"percentile": {"falsepos": 0.0028620682978568457}, "uncategorized": {"n_docs": 47005}}, "set": {"binary": {"distinct": 207, "loss": 0.0424867257200624}, "percentile": {"index": 7.5379623782261795, "non_null": 0.01549758994555206}, "test": {"time": 8.851617252674657}}, "support": {"binary": {"meanscore": 0.9933764632729682}, "percentile": {"exp_cost": 110241}, "test": {"prediction_time": 20.020428529086036}, "uncategorized": {"loss": 0.011125561725077615}}}, "reports": {"product": {"percentile": {"time": 5.95718424224943}, "test": {"n_docs": 58308}, "uncategorized": {"entropy": 2.439292407209559}}, "props": {"entities": {"falsepos": 0.04907411453073296, "non_null": 0.01553006502056653}, "uncategorized": {"index": 6.658861249536571, "size": 86062}}, "related": {"binary": {"auc": 0.9777353574927383, "time": 5.346454048446222}, "entities": {"avg_time": 5.801395505928203}, "percentile": {"precision": 0.9903021321103773}, "test": {"f1-score": 0.9501439846767683, "prediction_time": 8.250908409146682}}, "set": {"binary": {"f1-score": 0.8406852774029401, "non_null": 0.0032679915221176525, "size": 88533}, "percentile": {"non_null": 0.05052985610063654}, "test": {"auc": 0.9243323970053449, "distinct": 140}, "uncategorized": {"weighted_avg": 2.727498566458559}}, "support": {"binary": {"exp_cost": 202663, "size": 397581}, "entities": {"precision": 0.8996920720715197}, "percentile": {"avg_time": 5.991432637232433}, "test": {"exp_cost": 114955}, "uncategorized": {"avg_time": 6.848796526446567}}}, "results": {"product": {"binary": {"n_docs": 47983}, "uncategorized": {"loss": 0.004251934729631368}}, "props": {"percentile": {"index": 2.8788428626788174}, "test": {"non_null": 0.07694243128775269, "weighted_avg": 2.2559205978601815}}, "related": {"binary": {"falsepos": 0.01998714114423228, "loss": 0.009069745078332692}, "entities": {"prediction_time": 5.097030416855417}, "percentile": {"errors": 187}, "test": {"distinct": 190}, "uncategorized": {"loss": 0.008598437380083812}}, "set": {"percentile": {"time": 5.1639600334070375}, "test": {"precision": 0.9928572798261506}}, "support": {"binary": {"distinct": 187}, "test": {"f1-score": 0.9971622861152043}, "uncategorized": {"loss": 0.020110098144604738}}}, "train": {"product": {"binary": {"f1-score": 0.9430850286909084, "weighted_avg": 2.7079186029017825}, "entities": {"distinct": 179, "falsepos": 0.10116323026379015}, "percentile": {"auc": 0.9507543806281451}}, "props": {"test": {"distinct": 155}}, "related": {"entities": {"prediction_time": 3.0503064886423763}, "percentile": {"time": 7.11926330820841}, "test": {"errors": 197}, "uncategorized": {"time": 4.490368242102026}}, "set": {"entities": {"loss": 0.009078805739605178}, "percentile": {"prediction_time": 5.080648613057821}, "test": {"benchmark": 1.771960108777585, "recall": 0.9148139886399282}}, "support": {"binary": {"falsepos": 0.0528544805547323}, "entities": {"auc": 0.9601167222888196}, "percentile": {"benchmark": 2.351453170666186}, "uncategorized": {"time": 10.7962928147037}}}}