{"branch": {"product": {"binary": {"avg_time": 15926220.297429265, "meanscore": 1.0, "n_docs": 53277524623781027840}, "percentile": {"falsepos": 0.0}, "test": {"distinct": 1816, "exp_cost": 132743085568730192}, "uncategorized": {"errors": 1845}}, "props": {"binary": {"auc": 1.0, "distinct": 1785}, "entities": {"non_null": 0.0}, "uncategorized": {"benchmark": 19.7274158303633}}, "related": {"binary": {"fullscore": 1.0}, "percentile": {"time": 52027220.32211632}, "test": {"n_docs": 24939669460733}}, "set": {"binary": {"falsepos": 0.0}, "entities": {"avg_time": 10781326.739645682}, "test": {"entropy": 15.149621183403983, "exp_cost": 4350863337493126}}, "support": {"binary": {"distinct": 2218}}}, "brand": {"product": {"percentile": {"errors": 1388, "index": 893632196.1393002}, "uncategorized": {"exp_cost": 889947201363448064, "f1-score": 1.0, "recall": 1.0}}, "props": {"binary": {"exp_cost": 3972974654721879552}, "entities": {"index": 13744697780.910069}, "percentile": {"distinct": 1764, "index": 169494.9389285737, "weighted_avg": 18.72947545231272}}, "related": {"percentile": {"falsepos": 0.0}, "uncategorized": {"n_docs": 17521082260765268}}, "set": {"binary": {"distinct": 1704, "loss": 0.0}, "percentile": {"index": 95356454.08111675, "non_null": 0.0}, "test": {"time": 18355342.877958354}}, "support": {"binary": {"meanscore": 1.0}, "percentile": {"exp_cost": 87364323528328937472}, "test": {"prediction_time": 64003900891.7059}, "uncategorized": {"loss": 0.0}}}, "reports": {"product": {"percentile": {"time": 1022043.9375277081}, "test": {"n_docs": 11953590210207762}, "uncategorized": {"entropy": 23.637090528844123}}, "props": {"entities": {"falsepos": 0.0, "non_null": 0.0}, "uncategorized": {"index": 3385679.779481554, "size": 1292513560456054784}}, "related": {"binary": {"auc": 1.0, "time": 1323052.856247274}, "entities": {"avg_time": 3180653.5389307262}, "percentile": {"precision": 1.0}, "test": {"f1-score": 1.0, "prediction_time": 239484.3631914302}}, "set": {"binary": {"f1-score": 1.0, "non_null": 0.0, "size": 85544334790386286592}, "percentile": {"non_null": 0.0}, "test": {"auc": 1.0, "distinct": 1566}, "uncategorized": {"weighted_avg": 23.609258439944483}}, "support": {"binary": {"exp_cost": 6615598501406142627840, "size": 786595333854644756545536}, "entities": {"precision": 1.0}, "percentile": {"avg_time": 4013318.6740939445}, "test": {"exp_cost": 75411612611874799616}, "uncategorized": {"avg_time": 51488906.9732465}}}, "results": {"product": {"binary": {"n_docs": 24989907708321128}, "uncategorized": {"loss": 0.0}}, "props": {"percentile": {"index": 17149.498033131673}, "test": {"non_null": 0.0, "weighted_avg": 17.801919194041407}}, "related": {"binary": {"falsepos": 0.0, "loss": 0.0}, "entities": {"prediction_time": 19648.28554164564}, "percentile": {"errors": 1291}, "test": {"distinct": 1520}, "uncategorized": {"loss": 0.0}}, "set": {"percentile": {"time": 1165873.924215422}, "test": {"precision": 1.0}}, "support": {"binary": {"distinct": 1754}, "test": {"f1-score": 1.0}, "uncategorized": {"loss": 0.0}}}, "train": {"product": {"binary": {"f1-score": 1.0, "weighted_avg": 22.94404415507874}, "entities": {"distinct": 1670, "falsepos": 0.0}, "percentile": {"auc": 1.0}}, "props": {"test": {"distinct": 1374}}, "related": {"entities": {"prediction_time": 60720.80112780811}, "percentile": {"time": 1812142.8292862542}, "test": {"errors": 1661}, "uncategorized": {"time": 18158.465082741273}}, "set": {"entities": {"loss": 0.0}, "percentile": {"prediction_time": 1085417.6141407762}, "test": {"benchmark": 16.7779237429315, "recall": 1.0}}, "support": {"binary": {"falsepos": 0.0}, "entities": {"auc": 1.0}, "percentile": {"benchmark": 15.93705086293953}, "uncategorized": {"time": 11208641.659624103}}}}