{"branch": {"product": {"binary": {"avg_time": 1.0640989581323023e+20, "meanscore": 1.0, "n_docs": 567318860123438860269029144432388770629697660780544}, "percentile": {"falsepos": 0.0}, "test": {"distinct": 5195, "exp_cost": 22669326495648067115493430071887543681417216}, "uncategorized": {"errors": 5183}}, "props": {"binary": {"auc": 1.0, "distinct": 4960}, "entities": {"non_null": 0.0}, "uncategorized": {"benchmark": 55.22311661564121}}, "related": {"binary": {"fullscore": 1.0}, "percentile": {"time": 4.870847621544205e+21}, "test": {"n_docs": 464612812757749997211256224743424}}, "set": {"binary": {"falsepos": 0.0}, "entities": {"avg_time": 5.169129100779586e+19}, "test": {"entropy": 42.650834879940064, "exp_cost": 677145040978889387263274063001649414144}}, "support": {"binary": {"distinct": 6276}}}, "brand": {"product": {"percentile": {"errors": 3908, "index": 1.33648655095943e+25}, "uncategorized": {"exp_cost": 314638333934804222571190261525225876192493568, "f1-score": 1.0, "recall": 1.0}}, "props": {"binary": {"exp_cost": 163646033619608220616867757101244547252220854272}, "entities": {"index": 3.4180781905221234e+28}, "percentile": {"distinct": 4929, "index": 484089057217232.06, "weighted_avg": 52.76198865710373}}, "related": {"percentile": {"falsepos": 0.0}, "uncategorized": {"n_docs": 6626079178573074242170317118446751449088}}, "set": {"binary": {"distinct": 4821, "loss": 0.0}, "percentile": {"index": 6.086844699015077e+22, "non_null": 0.0}, "test": {"time": 1.5101553830106818e+20}}, "support": {"binary": {"meanscore": 1.0}, "percentile": {"exp_cost": 407823623354077344006498302459945358652447465144320}, "test": {"prediction_time": 2.094269013560301e+30}, "uncategorized": {"loss": 0.0}}}, "reports": {"product": {"percentile": {"time": 1.079479661418982e+17}, "test": {"n_docs": 2943401374126835895729778809104941187072}, "uncategorized": {"entropy": 66.95393208227036}}, "props": {"entities": {"falsepos": 0.0, "non_null": 0.0}, "uncategorized": {"index": 1.4967785818813926e+18, "size": 2503541360934883766228528410463947531673927680}}, "related": {"binary": {"auc": 1.0, "time": 1.4085660290676928e+17}, "entities": {"avg_time": 2.6147078671032673e+18}, "percentile": {"precision": 1.0}, "test": {"f1-score": 1.0, "prediction_time": 754857115103047.8}}, "set": {"binary": {"f1-score": 1.0, "non_null": 0.0, "size": 1001873411547420633917581224629507049274952193671168}, "percentile": {"non_null": 0.0}, "test": {"auc": 1.0, "distinct": 4439}, "uncategorized": {"weighted_avg": 66.6486854963137}}, "support": {"binary": {"exp_cost": 187752647118122624482801949129078557776200547648153845760, "size": 73884339661322013126873334732081643686138713281697225736454144}, "entities": {"precision": 1.0}, "percentile": {"avg_time": 1.0754367458899872e+19}, "test": {"exp_cost": 127698685741189332945374934013594505751325780738048}, "uncategorized": {"avg_time": 6.156916693682001e+21}}}, "results": {"product": {"binary": {"n_docs": 18426046742737263543106493237684999290880}, "uncategorized": {"loss": 0.0}}, "props": {"percentile": {"index": 840931820677.6113}, "test": {"non_null": 0.0, "weighted_avg": 50.14875564289903}}, "related": {"binary": {"falsepos": 0.0, "loss": 0.0}, "entities": {"prediction_time": 864489318262.8561}, "percentile": {"errors": 3617}, "test": {"distinct": 4232}, "uncategorized": {"loss": 0.0}}, "set": {"percentile": {"time": 1.1231903777822144e+17}, "test": {"precision": 1.0}}, "support": {"binary": {"distinct": 4959}, "test": {"f1-score": 1.0}, "uncategorized": {"loss": 0.0}}}, "train": {"product": {"binary": {"f1-score": 1.0, "weighted_avg": 65.17547955295359}, "entities": {"distinct": 4773, "falsepos": 0.0}, "percentile": {"auc": 1.0}}, "props": {"test": {"distinct": 3928}}, "related": {"entities": {"prediction_time": 41123508087629.96}, "percentile": {"time": 2.8209087778425462e+17}, "test": {"errors": 4643}, "uncategorized": {"time": 324330301479.7897}}, "set": {"entities": {"loss": 0.0}, "percentile": {"prediction_time": 1.5160008053751453e+17}, "test": {"benchmark": 47.89237510552854, "recall": 1.0}}, "support": {"binary": {"falsepos": 0.0}, "entities": {"auc": 1.0}, "percentile": {"benchmark": 44.16889260537855}, "uncategorized": {"time": 4.314835307233859e+19}}}}