{"branch": {"product": {"binary": {"avg_time": 1493726834942927.0, "meanscore": 1.0, "n_docs": 1058215654562744946256839196620150013952}, "percentile": {"falsepos": 0.0}, "test": {"distinct": 3899, "exp_cost": 1784268690132176648581883113766912}, "uncategorized": {"errors": 3908}}, "props": {"binary": {"auc": 1.0, "distinct": 3781}, "entities": {"non_null": 0.0}, "uncategorized": {"benchmark": 41.92049163084585}}, "related": {"binary": {"fullscore": 1.0}, "percentile": {"time": 4.1694546481135656e+16}, "test": {"n_docs": 21656721324023065402671104}}, "set": {"binary": {"falsepos": 0.0}, "entities": {"avg_time": 1052452804272165.0}, "test": {"entropy": 32.246452501058606, "exp_cost": 1469993354789836782716422455296}}, "support": {"binary": {"distinct": 4739}}}, "brand": {"product": {"percentile": {"errors": 2925, "index": 7.823066274294533e+18}, "uncategorized": {"exp_cost": 22423076191623403319357941028487168, "f1-score": 1.0, "recall": 1.0}}, "props": {"binary": {"exp_cost": 2372052394353626331642618603664048128}, "entities": {"index": 3.726430867028046e+21}, "percentile": {"distinct": 3733, "index": 125504101416.96767, "weighted_avg": 39.653199038562136}}, "related": {"percentile": {"falsepos": 0.0}, "uncategorized": {"n_docs": 4816608307423990099988319305728}}, "set": {"binary": {"distinct": 3605, "loss": 0.0}, "percentile": {"index": 1.363246123259952e+17, "non_null": 0.0}, "test": {"time": 2170955926465332.2}}, "support": {"binary": {"meanscore": 1.0}, "percentile": {"exp_cost": 1461086893994459957469548889207040114688}, "test": {"prediction_time": 8.525348893198317e+22}, "uncategorized": {"loss": 0.0}}}, "reports": {"product": {"percentile": {"time": 8013893648316.026}, "test": {"n_docs": 4609269027205786511476843872256}, "uncategorized": {"entropy": 50.729649813887285}}, "props": {"entities": {"falsepos": 0.0, "non_null": 0.0}, "uncategorized": {"index": 56378887017729.58, "size": 55809337818437905721266691888906240}}, "related": {"binary": {"auc": 1.0, "time": 8293982488436.797}, "entities": {"avg_time": 81645523213904.0}, "percentile": {"precision": 1.0}, "test": {"f1-score": 1.0, "prediction_time": 221361875796.64758}}, "set": {"binary": {"f1-score": 1.0, "non_null": 0.0, "size": 966738484560137379857977127360960397312}, "percentile": {"non_null": 0.0}, "test": {"auc": 1.0, "distinct": 3341}, "uncategorized": {"weighted_avg": 50.311663241659126}}, "support": {"binary": {"exp_cost": 25754722108034240158949178496644299700043776, "size": 290152239245406399953508823472021574169531514880}, "entities": {"precision": 1.0}, "percentile": {"avg_time": 165881669743738.53}, "test": {"exp_cost": 430548918243897344060546256372322271232}, "uncategorized": {"avg_time": 2.5553502223728956e+16}}}, "results": {"product": {"binary": {"n_docs": 20295808385880112719029916925952}, "uncategorized": {"loss": 0.0}}, "props": {"percentile": {"index": 1032065893.8457531}, "test": {"non_null": 0.0, "weighted_avg": 38.02727860922113}}, "related": {"binary": {"falsepos": 0.0, "loss": 0.0}, "entities": {"prediction_time": 1121544648.905155}, "percentile": {"errors": 2736}, "test": {"distinct": 3223}, "uncategorized": {"loss": 0.0}}, "set": {"percentile": {"time": 9298264215765.072}, "test": {"precision": 1.0}}, "support": {"binary": {"distinct": 3736}, "test": {"f1-score": 1.0}, "uncategorized": {"loss": 0.0}}}, "train": {"product": {"binary": {"f1-score": 1.0, "weighted_avg": 49.189196799520076}, "entities": {"distinct": 3569, "falsepos": 0.0}, "percentile": {"auc": 1.0}}, "props": {"test": {"distinct": 2970}}, "related": {"entities": {"prediction_time": 19322837293.43518}, "percentile": {"time": 17088837062974.965}, "test": {"errors": 3502}, "uncategorized": {"time": 542583612.9400547}}, "set": {"entities": {"loss": 0.0}, "percentile": {"prediction_time": 9759320233830.889}, "test": {"benchmark": 36.32951301757552, "recall": 1.0}}, "support": {"binary": {"falsepos": 0.0}, "entities": {"auc": 1.0}, "percentile": {"benchmark": 33.30894231820413}, "uncategorized": {"time": 665617487783776.6}}}}