{"branch": {"product": {"binary": {"avg_time": 3.3514460886120806e+18, "meanscore": 1.0, "n_docs": 87840999936907637747332031856931376634580172800}, "percentile": {"falsepos": 0.0}, "test": {"distinct": 4796, "exp_cost": 15184776770117593386461635489088097222656}, "uncategorized": {"errors": 4803}}, "props": {"binary": {"auc": 1.0, "distinct": 4604}, "entities": {"non_null": 0.0}, "uncategorized": {"benchmark": 51.06689714916168}}, "related": {"binary": {"fullscore": 1.0}, "percentile": {"time": 1.5733863536426677e+20}, "test": {"n_docs": 2100570426037170063717223628800}}, "set": {"binary": {"falsepos": 0.0}, "entities": {"avg_time": 1.8321277891535222e+18}, "test": {"entropy": 39.40088178249636, "exp_cost": 1575175814948334006382419318105178112}}, "support": {"binary": {"distinct": 5808}}}, "brand": {"product": {"percentile": {"errors": 3595, "index": 1.433184185529983e+23}, "uncategorized": {"exp_cost": 302405838857553399799788041290250400563200, "f1-score": 1.0, "recall": 1.0}}, "props": {"binary": {"exp_cost": 71691224135553940743995082408866900875411456}, "entities": {"index": 2.4322934678146978e+26}, "percentile": {"distinct": 4561, "index": 40493329125296.58, "weighted_avg": 48.70224213440271}}, "related": {"percentile": {"falsepos": 0.0}, "uncategorized": {"n_docs": 9876432618620824245575991871768887296}}, "set": {"binary": {"distinct": 4442, "loss": 0.0}, "percentile": {"index": 9.009307021692999e+20, "non_null": 0.0}, "test": {"time": 5.609803937055362e+18}}, "support": {"binary": {"meanscore": 1.0}, "percentile": {"exp_cost": 134186208734424449321962268641340562064342515712}, "test": {"prediction_time": 1.3937349766326507e+28}, "uncategorized": {"loss": 0.0}}}, "reports": {"product": {"percentile": {"time": 5213785149795909.0}, "test": {"n_docs": 4345477297800515957681668505338904576}, "uncategorized": {"entropy": 62.068992168522456}}, "props": {"entities": {"falsepos": 0.0, "non_null": 0.0}, "uncategorized": {"index": 6.525082847106656e+16, "size": 1134957877170744234164029773018296389468160}}, "related": {"binary": {"auc": 1.0, "time": 7772227894486181.0}, "entities": {"avg_time": 1.0526488226588032e+17}, "percentile": {"precision": 1.0}, "test": {"f1-score": 1.0, "prediction_time": 63820401418388.07}}, "set": {"binary": {"f1-score": 1.0, "non_null": 0.0, "size": 204105765946972758363676093453919915385496272896}, "percentile": {"non_null": 0.0}, "test": {"auc": 1.0, "distinct": 4099}, "uncategorized": {"weighted_avg": 61.567054991792396}}, "support": {"binary": {"exp_cost": 12556688864484097992716500024749576914601963291672576, "size": 1410827266781663713333681196179029126866318849695012618240}, "entities": {"precision": 1.0}, "percentile": {"avg_time": 3.2203025382410086e+17}, "test": {"exp_cost": 45224691535181692486866205873627158360841256960}, "uncategorized": {"avg_time": 1.094392796998819e+20}}}, "results": {"product": {"binary": {"n_docs": 28308480254929393995181326192856793088}, "uncategorized": {"loss": 0.0}}, "props": {"percentile": {"index": 107949641382.87267}, "test": {"non_null": 0.0, "weighted_avg": 46.45401592440066}}, "related": {"binary": {"falsepos": 0.0, "loss": 0.0}, "entities": {"prediction_time": 108757351059.74045}, "percentile": {"errors": 3330}, "test": {"distinct": 3939}, "uncategorized": {"loss": 0.0}}, "set": {"percentile": {"time": 6488815528602976.0}, "test": {"precision": 1.0}}, "support": {"binary": {"distinct": 4592}, "test": {"f1-score": 1.0}, "uncategorized": {"loss": 0.0}}}, "train": {"product": {"binary": {"f1-score": 1.0, "weighted_avg": 60.25458378454432}, "entities": {"distinct": 4389, "falsepos": 0.0}, "percentile": {"auc": 1.0}}, "props": {"test": {"distinct": 3638}}, "related": {"entities": {"prediction_time": 4263674775215.9883}, "percentile": {"time": 1.436104464136897e+16}, "test": {"errors": 4301}, "uncategorized": {"time": 44319593116.80243}}, "set": {"entities": {"loss": 0.0}, "percentile": {"prediction_time": 6900710311588583.0}, "test": {"benchmark": 44.30784416852238, "recall": 1.0}}, "support": {"binary": {"falsepos": 0.0}, "entities": {"auc": 1.0}, "percentile": {"benchmark": 40.77053356356585}, "uncategorized": {"time": 1.3794001131294154e+18}}}}