{"branch": {"product": {"binary": {"avg_time": 485.36086638041803, "meanscore": 0.9999999997239292, "n_docs": 976309723}, "percentile": {"falsepos": 1.7253309891884783e-11}, "test": {"distinct": 660, "exp_cost": 133811317}, "uncategorized": {"errors": 679}}, "props": {"binary": {"auc": 0.9999999999999902, "distinct": 655}, "entities": {"non_null": 1.8549139668699866e-08}, "uncategorized": {"benchmark": 7.357184851334401}}, "related": {"binary": {"fullscore": 0.9999639107219902}, "percentile": {"time": 567.72185135201}, "test": {"n_docs": 9257070}}, "set": {"binary": {"falsepos": 1.659241632978592e-10}, "entities": {"avg_time": 377.414288822857}, "test": {"entropy": 5.639990010385573, "exp_cost": 33016250}}, "support": {"binary": {"distinct": 788}}}, "brand": {"product": {"percentile": {"errors": 500, "index": 2142.2407825077803}, "uncategorized": {"exp_cost": 330226282, "f1-score": 0.9999999999673987, "recall": 0.9999999999963803}}, "props": {"binary": {"exp_cost": 452751730}, "entities": {"index": 4593.689861169217}, "percentile": {"distinct": 644, "index": 88.01621980845742, "weighted_avg": 6.973196840912172}}, "related": {"percentile": {"falsepos": 1.9984014443252818e-15}, "uncategorized": {"n_docs": 95334556}}, "set": {"binary": {"distinct": 630, "loss": 1.007713343881278e-07}, "percentile": {"index": 690.071238781426, "non_null": 1.5970336164627952e-11}, "test": {"time": 480.819042739599}}, "support": {"binary": {"meanscore": 0.9999999999999615}, "percentile": {"exp_cost": 1595027561}, "test": {"prediction_time": 9812.669413235211}, "uncategorized": {"loss": 1.3854806191204716e-11}}}, "reports": {"product": {"percentile": {"time": 162.6772890089913}, "test": {"n_docs": 79058614}, "uncategorized": {"entropy": 8.506240364304686}}, "props": {"entities": {"falsepos": 9.136789613783947e-08, "non_null": 1.6557751836288048e-09}, "uncategorized": {"index": 313.5344569533288, "size": 557741106}}, "related": {"binary": {"auc": 0.9999999799772868, "time": 172.15969019399236}, "entities": {"avg_time": 215.95658814528}, "percentile": {"precision": 0.9999999999996708}, "test": {"f1-score": 0.9999980007452385, "prediction_time": 142.56387409787487}}, "set": {"binary": {"f1-score": 0.9999446768408321, "non_null": 0.0, "size": 1409801531}, "percentile": {"non_null": 5.227686061815007e-10}, "test": {"auc": 0.9999908439226698, "distinct": 554}, "uncategorized": {"weighted_avg": 8.649031466947788}}, "support": {"binary": {"exp_cost": 4776278347, "size": 50294269675}, "entities": {"precision": 0.9999834367993852}, "percentile": {"avg_time": 247.7762860163729}, "test": {"exp_cost": 2952594260}, "uncategorized": {"avg_time": 608.1882978906075}}}, "results": {"product": {"binary": {"n_docs": 96669805}, "uncategorized": {"loss": 7.993605777301127e-15}}, "props": {"percentile": {"index": 28.55925430294892}, "test": {"non_null": 7.820971170224844e-05, "weighted_avg": 6.534862513788653}}, "related": {"binary": {"falsepos": 1.0205725153866751e-10, "loss": 3.341771304121721e-14}, "entities": {"prediction_time": 45.15897281708534}, "percentile": {"errors": 490}, "test": {"distinct": 556}, "uncategorized": {"loss": 3.206324095117452e-13}}, "set": {"percentile": {"time": 178.45570113232876}, "test": {"precision": 0.9999999999037119}}, "support": {"binary": {"distinct": 645}, "test": {"f1-score": 1.0}, "uncategorized": {"loss": 8.720952848761954e-10}}}, "train": {"product": {"binary": {"f1-score": 0.9999984000262386, "weighted_avg": 8.249160332544058}, "entities": {"distinct": 600, "falsepos": 3.353864920518923e-05}, "percentile": {"auc": 0.9999999994125286}}, "props": {"test": {"distinct": 504}}, "related": {"entities": {"prediction_time": 43.30652898511509}, "percentile": {"time": 206.16636447172058}, "test": {"errors": 611}, "uncategorized": {"time": 44.52688329467319}}, "set": {"entities": {"loss": 7.549516567451064e-15}, "percentile": {"prediction_time": 166.97407251284977}, "test": {"benchmark": 5.839798698812845, "recall": 0.9999804785180315}}, "support": {"binary": {"falsepos": 7.074359926750873e-07}, "entities": {"auc": 0.9999990547193287}, "percentile": {"benchmark": 6.1745063288188815}, "uncategorized": {"time": 528.2667097893502}}}}