{"branch": {"product": {"binary": {"avg_time": 1397148504408.83, "meanscore": 1.0, "n_docs": 46328273062511678814218927210496}, "percentile": {"falsepos": 0.0}, "test": {"distinct": 3072, "exp_cost": 758828071986568924978216960}, "uncategorized": {"errors": 3123}}, "props": {"binary": {"auc": 1.0, "distinct": 3063}, "entities": {"non_null": 0.0}, "uncategorized": {"benchmark": 33.61671722843665}}, "related": {"binary": {"fullscore": 1.0}, "percentile": {"time": 28662177004368.93}, "test": {"n_docs": 656623367802346274816}}, "set": {"binary": {"falsepos": 0.0}, "entities": {"avg_time": 1542640053810.2415}, "test": {"entropy": 25.836516990765222, "exp_cost": 5744101073069749512962048}}, "support": {"binary": {"distinct": 3815}}}, "brand": {"product": {"percentile": {"errors": 2305, "index": 929228412908779.9}, "uncategorized": {"exp_cost": 10953867261516054373582503936, "f1-score": 1.0, "recall": 1.0}}, "props": {"binary": {"exp_cost": 559865933967330409097098952704}, "entities": {"index": 1.8758933023534813e+17}, "percentile": {"distinct": 2985, "index": 692200731.2397859, "weighted_avg": 31.395526533763952}}, "related": {"percentile": {"falsepos": 0.0}, "uncategorized": {"n_docs": 9541572603021648713482240}}, "set": {"binary": {"distinct": 2836, "loss": 0.0}, "percentile": {"index": 50808439966686.74, "non_null": 0.0}, "test": {"time": 2592266986640.1997}}, "support": {"binary": {"meanscore": 1.0}, "percentile": {"exp_cost": 146275050904016466538847828705280}, "test": {"prediction_time": 2.389080689110366e+18}, "uncategorized": {"loss": 0.0}}}, "reports": {"product": {"percentile": {"time": 20995897826.486885}, "test": {"n_docs": 28553440350430413723795456}, "uncategorized": {"entropy": 40.43826053048264}}, "props": {"entities": {"falsepos": 0.0, "non_null": 0.0}, "uncategorized": {"index": 104777899612.8722, "size": 13977046825114887421656301568}}, "related": {"binary": {"auc": 1.0, "time": 23466128182.143383}, "entities": {"avg_time": 134106322967.41258}, "percentile": {"precision": 1.0}, "test": {"f1-score": 1.0, "prediction_time": 1477541509.3810713}}, "set": {"binary": {"f1-score": 1.0, "non_null": 0.0, "size": 42343012132995026973806452277248}, "percentile": {"non_null": 0.0}, "test": {"auc": 1.0, "distinct": 2659}, "uncategorized": {"weighted_avg": 40.19301114548784}}, "support": {"binary": {"exp_cost": 276879264005903365447614864103047168, "size": 239858814468988477436415907427801628672}, "entities": {"precision": 1.0}, "percentile": {"avg_time": 129631887152.54082}, "test": {"exp_cost": 32790301871768688272491233148928}, "uncategorized": {"avg_time": 11994985061698.092}}}, "results": {"product": {"binary": {"n_docs": 42287271228190894334148608}, "uncategorized": {"loss": 0.0}}, "props": {"percentile": {"index": 14792168.451897465}, "test": {"non_null": 0.0, "weighted_avg": 30.639572465852776}}, "related": {"binary": {"falsepos": 0.0, "loss": 0.0}, "entities": {"prediction_time": 15341805.371252036}, "percentile": {"errors": 2190}, "test": {"distinct": 2632}, "uncategorized": {"loss": 0.0}}, "set": {"percentile": {"time": 24693363850.500195}, "test": {"precision": 1.0}}, "support": {"binary": {"distinct": 2949}, "test": {"f1-score": 1.0}, "uncategorized": {"loss": 0.0}}}, "train": {"product": {"binary": {"f1-score": 1.0, "weighted_avg": 39.26514343617681}, "entities": {"distinct": 2803, "falsepos": 0.0}, "percentile": {"auc": 1.0}}, "props": {"test": {"distinct": 2374}}, "related": {"entities": {"prediction_time": 132446941.40026556}, "percentile": {"time": 55641560674.51696}, "test": {"errors": 2790}, "uncategorized": {"time": 10771204.075455204}}, "set": {"entities": {"loss": 0.0}, "percentile": {"prediction_time": 24222667754.179543}, "test": {"benchmark": 29.492340643940246, "recall": 1.0}}, "support": {"binary": {"falsepos": 0.0}, "entities": {"auc": 1.0}, "percentile": {"benchmark": 26.483602149793803}, "uncategorized": {"time": 601529007764.6909}}}}